{"config": {"view": {"continuousWidth": 400, "continuousHeight": 300}}, "hconcat": [{"mark": "rect", "encoding": {"color": {"field": "Dog Population (in 1000)", "scale": {"scheme": "goldorange"}, "type": "quantitative"}, "x": {"bin": {"maxbins": 11}, "field": "Mean Number of Dogs per household", "type": "quantitative"}, "y": {"field": "Location", "type": "ordinal"}}, "height": 900, "selection": {"selector001": {"type": "interval", "encodings": ["x", "y"]}}, "width": 300}, {"mark": "bar", "encoding": {"color": {"field": "Location", "type": "nominal"}, "x": {"axis": {"title": "Location"}, "field": "Location", "sort": "-y", "type": "nominal"}, "y": {"axis": {"title": "Cat Population"}, "field": "Cat Population", "type": "quantitative"}}, "height": 300, "transform": [{"filter": {"selection": "selector001"}}]}], "data": {"name": "data-268d03f0a674f39b983c092628b8ab7b"}, "$schema": "https://vega.github.io/schema/vega-lite/v4.17.0.json", "datasets": {"data-268d03f0a674f39b983c092628b8ab7b": [{"Location": "Alabama", "Number of Households (in 1000)": 1828, "Percentage of households with pets": 59.5, "Number of Pet Households (in 1000)": 1088, "Percentage of Dog Owners": 44.1, "Dog Owning Households (1000s)": 807, "Mean Number of Dogs per household": 1.7, "Dog Population (in 1000)": 1410, "Percentage of Cat Owners": 27.4, "Cat Owning Households": 501, "Mean Number of Cats": 2.5, "Cat Population": 1252}, {"Location": "Arizona", "Number of Households (in 1000)": 2515, "Percentage of households with pets": 59.5, "Number of Pet Households (in 1000)": 1497, "Percentage of Dog Owners": 40.1, "Dog Owning Households (1000s)": 1008, "Mean Number of Dogs per household": 1.8, "Dog Population (in 1000)": 1798, "Percentage of Cat Owners": 29.6, "Cat Owning Households": 743, "Mean Number of Cats": 1.9, "Cat Population": 1438}, {"Location": "Arkansas", "Number of Households (in 1000)": 1148, "Percentage of households with pets": 62.4, "Number of Pet Households (in 1000)": 716, "Percentage of Dog Owners": 47.9, "Dog Owning Households (1000s)": 550, "Mean Number of Dogs per household": 2.0, "Dog Population (in 1000)": 1097, "Percentage of Cat Owners": 30.6, "Cat Owning Households": 351, "Mean Number of Cats": 2.3, "Cat Population": 810}, {"Location": "California", "Number of Households (in 1000)": 12974, "Percentage of households with pets": 52.9, "Number of Pet Households (in 1000)": 6865, "Percentage of Dog Owners": 32.8, "Dog Owning Households (1000s)": 4260, "Mean Number of Dogs per household": 1.6, "Dog Population (in 1000)": 6687, "Percentage of Cat Owners": 28.3, "Cat Owning Households": 3687, "Mean Number of Cats": 1.9, "Cat Population": 7118}, {"Location": "Colorado", "Number of Households (in 1000)": 1986, "Percentage of households with pets": 61.3, "Number of Pet Households (in 1000)": 1217, "Percentage of Dog Owners": 42.5, "Dog Owning Households (1000s)": 845, "Mean Number of Dogs per household": 1.6, "Dog Population (in 1000)": 1349, "Percentage of Cat Owners": 32.3, "Cat Owning Households": 642, "Mean Number of Cats": 1.9, "Cat Population": 1191}, {"Location": "Connecticut", "Number of Households (in 1000)": 1337, "Percentage of households with pets": 54.4, "Number of Pet Households (in 1000)": 728, "Percentage of Dog Owners": 28.3, "Dog Owning Households (1000s)": 379, "Mean Number of Dogs per household": 1.3, "Dog Population (in 1000)": 507, "Percentage of Cat Owners": 31.9, "Cat Owning Households": 427, "Mean Number of Cats": 1.9, "Cat Population": 796}, {"Location": "Delaware", "Number of Households (in 1000)": 334, "Percentage of households with pets": 56.6, "Number of Pet Households (in 1000)": 189, "Percentage of Dog Owners": 33.7, "Dog Owning Households (1000s)": 113, "Mean Number of Dogs per household": 1.4, "Dog Population (in 1000)": 163, "Percentage of Cat Owners": 33.7, "Cat Owning Households": 113, "Mean Number of Cats": 1.7, "Cat Population": 187}, {"Location": "District of Columbia", "Number of Households (in 1000)": 287, "Percentage of households with pets": 21.9, "Number of Pet Households (in 1000)": 63, "Percentage of Dog Owners": 13.1, "Dog Owning Households (1000s)": 38, "Mean Number of Dogs per household": 1.1, "Dog Population (in 1000)": 42, "Percentage of Cat Owners": 11.6, "Cat Owning Households": 33, "Mean Number of Cats": 1.9, "Cat Population": 63}, {"Location": "Florida", "Number of Households (in 1000)": 7609, "Percentage of households with pets": 54.4, "Number of Pet Households (in 1000)": 4138, "Percentage of Dog Owners": 35.7, "Dog Owning Households (1000s)": 2718, "Mean Number of Dogs per household": 1.5, "Dog Population (in 1000)": 4210, "Percentage of Cat Owners": 27.3, "Cat Owning Households": 2079, "Mean Number of Cats": 2.1, "Cat Population": 4375}, {"Location": "Georgia", "Number of Households (in 1000)": 3798, "Percentage of households with pets": 55.1, "Number of Pet Households (in 1000)": 2093, "Percentage of Dog Owners": 40.1, "Dog Owning Households (1000s)": 1522, "Mean Number of Dogs per household": 1.6, "Dog Population (in 1000)": 2479, "Percentage of Cat Owners": 27.3, "Cat Owning Households": 1037, "Mean Number of Cats": 2.1, "Cat Population": 2162}, {"Location": "Idaho", "Number of Households (in 1000)": 568, "Percentage of households with pets": 62.0, "Number of Pet Households (in 1000)": 352, "Percentage of Dog Owners": 42.7, "Dog Owning Households (1000s)": 242, "Mean Number of Dogs per household": 1.5, "Dog Population (in 1000)": 357, "Percentage of Cat Owners": 34.6, "Cat Owning Households": 196, "Mean Number of Cats": 2.0, "Cat Population": 393}, {"Location": "Illinois", "Number of Households (in 1000)": 5026, "Percentage of households with pets": 51.8, "Number of Pet Households (in 1000)": 2602, "Percentage of Dog Owners": 32.4, "Dog Owning Households (1000s)": 1627, "Mean Number of Dogs per household": 1.5, "Dog Population (in 1000)": 2365, "Percentage of Cat Owners": 26.3, "Cat Owning Households": 1321, "Mean Number of Cats": 1.9, "Cat Population": 2453}, {"Location": "Indiana", "Number of Households (in 1000)": 2478, "Percentage of households with pets": 59.9, "Number of Pet Households (in 1000)": 1484, "Percentage of Dog Owners": 39.9, "Dog Owning Households (1000s)": 989, "Mean Number of Dogs per household": 1.6, "Dog Population (in 1000)": 1619, "Percentage of Cat Owners": 34.4, "Cat Owning Households": 852, "Mean Number of Cats": 2.2, "Cat Population": 1912}, {"Location": "Iowa", "Number of Households (in 1000)": 1219, "Percentage of households with pets": 53.6, "Number of Pet Households (in 1000)": 654, "Percentage of Dog Owners": 33.4, "Dog Owning Households (1000s)": 407, "Mean Number of Dogs per household": 1.5, "Dog Population (in 1000)": 610, "Percentage of Cat Owners": 30.3, "Cat Owning Households": 370, "Mean Number of Cats": 2.2, "Cat Population": 805}, {"Location": "Kansas", "Number of Households (in 1000)": 1133, "Percentage of households with pets": 61.0, "Number of Pet Households (in 1000)": 691, "Percentage of Dog Owners": 42.3, "Dog Owning Households (1000s)": 480, "Mean Number of Dogs per household": 1.6, "Dog Population (in 1000)": 774, "Percentage of Cat Owners": 33.3, "Cat Owning Households": 378, "Mean Number of Cats": 1.9, "Cat Population": 731}, {"Location": "Kentucky", "Number of Households (in 1000)": 1777, "Percentage of households with pets": 61.6, "Number of Pet Households (in 1000)": 1094, "Percentage of Dog Owners": 45.9, "Dog Owning Households (1000s)": 816, "Mean Number of Dogs per household": 1.9, "Dog Population (in 1000)": 1531, "Percentage of Cat Owners": 36.8, "Cat Owning Households": 654, "Mean Number of Cats": 2.1, "Cat Population": 1349}, {"Location": "Louisiana", "Number of Households (in 1000)": 1702, "Percentage of households with pets": 55.1, "Number of Pet Households (in 1000)": 937, "Percentage of Dog Owners": 36.4, "Dog Owning Households (1000s)": 619, "Mean Number of Dogs per household": 1.8, "Dog Population (in 1000)": 1115, "Percentage of Cat Owners": 25.9, "Cat Owning Households": 441, "Mean Number of Cats": 2.0, "Cat Population": 877}, {"Location": "Maine", "Number of Households (in 1000)": 548, "Percentage of households with pets": 62.9, "Number of Pet Households (in 1000)": 345, "Percentage of Dog Owners": 34.6, "Dog Owning Households (1000s)": 190, "Mean Number of Dogs per household": 1.6, "Dog Population (in 1000)": 300, "Percentage of Cat Owners": 46.4, "Cat Owning Households": 254, "Mean Number of Cats": 1.9, "Cat Population": 498}, {"Location": "Maryland", "Number of Households (in 1000)": 2169, "Percentage of households with pets": 52.3, "Number of Pet Households (in 1000)": 1134, "Percentage of Dog Owners": 30.8, "Dog Owning Households (1000s)": 667, "Mean Number of Dogs per household": 1.4, "Dog Population (in 1000)": 915, "Percentage of Cat Owners": 29.8, "Cat Owning Households": 645, "Mean Number of Cats": 2.6, "Cat Population": 1677}, {"Location": "Massachusetts", "Number of Households (in 1000)": 2618, "Percentage of households with pets": 50.4, "Number of Pet Households (in 1000)": 1318, "Percentage of Dog Owners": 23.6, "Dog Owning Households (1000s)": 618, "Mean Number of Dogs per household": 1.4, "Dog Population (in 1000)": 850, "Percentage of Cat Owners": 34.1, "Cat Owning Households": 892, "Mean Number of Cats": 1.8, "Cat Population": 1593}, {"Location": "Michigan", "Number of Households (in 1000)": 3804, "Percentage of households with pets": 55.4, "Number of Pet Households (in 1000)": 2108, "Percentage of Dog Owners": 34.6, "Dog Owning Households (1000s)": 1318, "Mean Number of Dogs per household": 1.5, "Dog Population (in 1000)": 2036, "Percentage of Cat Owners": 31.3, "Cat Owning Households": 1192, "Mean Number of Cats": 2.0, "Cat Population": 2420}, {"Location": "Minnesota", "Number of Households (in 1000)": 2163, "Percentage of households with pets": 53.0, "Number of Pet Households (in 1000)": 1146, "Percentage of Dog Owners": 31.9, "Dog Owning Households (1000s)": 690, "Mean Number of Dogs per household": 1.4, "Dog Population (in 1000)": 934, "Percentage of Cat Owners": 29.7, "Cat Owning Households": 643, "Mean Number of Cats": 2.0, "Cat Population": 1264}, {"Location": "Mississippi", "Number of Households (in 1000)": 1115, "Percentage of households with pets": 56.4, "Number of Pet Households (in 1000)": 629, "Percentage of Dog Owners": 45.2, "Dog Owning Households (1000s)": 504, "Mean Number of Dogs per household": 1.7, "Dog Population (in 1000)": 846, "Percentage of Cat Owners": 29.1, "Cat Owning Households": 324, "Mean Number of Cats": 2.1, "Cat Population": 668}, {"Location": "Missouri", "Number of Households (in 1000)": 2498, "Percentage of households with pets": 61.4, "Number of Pet Households (in 1000)": 1534, "Percentage of Dog Owners": 45.9, "Dog Owning Households (1000s)": 1148, "Mean Number of Dogs per household": 1.7, "Dog Population (in 1000)": 1978, "Percentage of Cat Owners": 32.2, "Cat Owning Households": 805, "Mean Number of Cats": 2.1, "Cat Population": 1653}, {"Location": "Montana", "Number of Households (in 1000)": 410, "Percentage of households with pets": 61.3, "Number of Pet Households (in 1000)": 251, "Percentage of Dog Owners": 41.2, "Dog Owning Households (1000s)": 169, "Mean Number of Dogs per household": 1.7, "Dog Population (in 1000)": 282, "Percentage of Cat Owners": 33.6, "Cat Owning Households": 138, "Mean Number of Cats": 2.0, "Cat Population": 277}, {"Location": "Nebraska", "Number of Households (in 1000)": 710, "Percentage of households with pets": 51.3, "Number of Pet Households (in 1000)": 364, "Percentage of Dog Owners": 33.8, "Dog Owning Households (1000s)": 240, "Mean Number of Dogs per household": 1.6, "Dog Population (in 1000)": 374, "Percentage of Cat Owners": 31.3, "Cat Owning Households": 222, "Mean Number of Cats": 2.3, "Cat Population": 514}, {"Location": "Nevada", "Number of Households (in 1000)": 986, "Percentage of households with pets": 55.6, "Number of Pet Households (in 1000)": 548, "Percentage of Dog Owners": 37.1, "Dog Owning Households (1000s)": 366, "Mean Number of Dogs per household": 1.6, "Dog Population (in 1000)": 578, "Percentage of Cat Owners": 30.3, "Cat Owning Households": 299, "Mean Number of Cats": 2.1, "Cat Population": 625}, {"Location": "New Hampshire", "Number of Households (in 1000)": 508, "Percentage of households with pets": 56.8, "Number of Pet Households (in 1000)": 289, "Percentage of Dog Owners": 30.3, "Dog Owning Households (1000s)": 154, "Mean Number of Dogs per household": 1.4, "Dog Population (in 1000)": 212, "Percentage of Cat Owners": 34.2, "Cat Owning Households": 174, "Mean Number of Cats": 1.8, "Cat Population": 309}, {"Location": "New Jersey", "Number of Households (in 1000)": 3177, "Percentage of households with pets": 50.7, "Number of Pet Households (in 1000)": 1611, "Percentage of Dog Owners": 32.4, "Dog Owning Households (1000s)": 1028, "Mean Number of Dogs per household": 1.3, "Dog Population (in 1000)": 1340, "Percentage of Cat Owners": 25.3, "Cat Owning Households": 803, "Mean Number of Cats": 1.8, "Cat Population": 1468}, {"Location": "New Mexico", "Number of Households (in 1000)": 773, "Percentage of households with pets": 67.6, "Number of Pet Households (in 1000)": 523, "Percentage of Dog Owners": 46.0, "Dog Owning Households (1000s)": 356, "Mean Number of Dogs per household": 2.0, "Dog Population (in 1000)": 703, "Percentage of Cat Owners": 32.0, "Cat Owning Households": 247, "Mean Number of Cats": 2.2, "Cat Population": 533}, {"Location": "New York", "Number of Households (in 1000)": 7512, "Percentage of households with pets": 50.6, "Number of Pet Households (in 1000)": 3802, "Percentage of Dog Owners": 29.0, "Dog Owning Households (1000s)": 2177, "Mean Number of Dogs per household": 1.4, "Dog Population (in 1000)": 3054, "Percentage of Cat Owners": 29.1, "Cat Owning Households": 2189, "Mean Number of Cats": 1.9, "Cat Population": 4261}, {"Location": "North Carolina", "Number of Households (in 1000)": 3701, "Percentage of households with pets": 56.4, "Number of Pet Households (in 1000)": 2089, "Percentage of Dog Owners": 40.3, "Dog Owning Households (1000s)": 1491, "Mean Number of Dogs per household": 1.7, "Dog Population (in 1000)": 2518, "Percentage of Cat Owners": 29.5, "Cat Owning Households": 1090, "Mean Number of Cats": 2.0, "Cat Population": 2220}, {"Location": "North Dakota", "Number of Households (in 1000)": 272, "Percentage of households with pets": 53.9, "Number of Pet Households (in 1000)": 147, "Percentage of Dog Owners": 36.1, "Dog Owning Households (1000s)": 98, "Mean Number of Dogs per household": 1.4, "Dog Population (in 1000)": 139, "Percentage of Cat Owners": 31.4, "Cat Owning Households": 85, "Mean Number of Cats": 2.0, "Cat Population": 174}, {"Location": "Ohio", "Number of Households (in 1000)": 4661, "Percentage of households with pets": 57.4, "Number of Pet Households (in 1000)": 2677, "Percentage of Dog Owners": 36.6, "Dog Owning Households (1000s)": 1708, "Mean Number of Dogs per household": 1.6, "Dog Population (in 1000)": 2730, "Percentage of Cat Owners": 33.3, "Cat Owning Households": 1553, "Mean Number of Cats": 2.4, "Cat Population": 3786}, {"Location": "Oklahoma", "Number of Households (in 1000)": 1479, "Percentage of households with pets": 58.9, "Number of Pet Households (in 1000)": 872, "Percentage of Dog Owners": 43.2, "Dog Owning Households (1000s)": 638, "Mean Number of Dogs per household": 2.1, "Dog Population (in 1000)": 1327, "Percentage of Cat Owners": 32.6, "Cat Owning Households": 482, "Mean Number of Cats": 2.2, "Cat Population": 1041}, {"Location": "Oregon", "Number of Households (in 1000)": 1505, "Percentage of households with pets": 63.6, "Number of Pet Households (in 1000)": 957, "Percentage of Dog Owners": 38.8, "Dog Owning Households (1000s)": 584, "Mean Number of Dogs per household": 1.6, "Dog Population (in 1000)": 917, "Percentage of Cat Owners": 40.2, "Cat Owning Households": 605, "Mean Number of Cats": 2.0, "Cat Population": 1185}, {"Location": "Pennsylvania", "Number of Households (in 1000)": 5172, "Percentage of households with pets": 56.9, "Number of Pet Households (in 1000)": 2942, "Percentage of Dog Owners": 32.9, "Dog Owning Households (1000s)": 1702, "Mean Number of Dogs per household": 1.5, "Dog Population (in 1000)": 2485, "Percentage of Cat Owners": 33.8, "Cat Owning Households": 1748, "Mean Number of Cats": 2.0, "Cat Population": 3544}, {"Location": "Rhode Island", "Number of Households (in 1000)": 434, "Percentage of households with pets": 53.0, "Number of Pet Households (in 1000)": 230, "Percentage of Dog Owners": 29.3, "Dog Owning Households (1000s)": 127, "Mean Number of Dogs per household": 1.3, "Dog Population (in 1000)": 161, "Percentage of Cat Owners": 27.6, "Cat Owning Households": 120, "Mean Number of Cats": 1.8, "Cat Population": 212}, {"Location": "South Carolina", "Number of Households (in 1000)": 1759, "Percentage of households with pets": 54.1, "Number of Pet Households (in 1000)": 951, "Percentage of Dog Owners": 38.6, "Dog Owning Households (1000s)": 678, "Mean Number of Dogs per household": 1.8, "Dog Population (in 1000)": 1191, "Percentage of Cat Owners": 27.8, "Cat Owning Households": 490, "Mean Number of Cats": 2.1, "Cat Population": 1039}, {"Location": "South Dakota", "Number of Households (in 1000)": 333, "Percentage of households with pets": 65.6, "Number of Pet Households (in 1000)": 219, "Percentage of Dog Owners": 42.8, "Dog Owning Households (1000s)": 143, "Mean Number of Dogs per household": 1.5, "Dog Population (in 1000)": 220, "Percentage of Cat Owners": 39.1, "Cat Owning Households": 130, "Mean Number of Cats": 2.2, "Cat Population": 290}, {"Location": "Tennessee", "Number of Households (in 1000)": 2583, "Percentage of households with pets": 59.6, "Number of Pet Households (in 1000)": 1540, "Percentage of Dog Owners": 44.1, "Dog Owning Households (1000s)": 1140, "Mean Number of Dogs per household": 1.9, "Dog Population (in 1000)": 2157, "Percentage of Cat Owners": 29.8, "Cat Owning Households": 770, "Mean Number of Cats": 2.3, "Cat Population": 1749}, {"Location": "Texas", "Number of Households (in 1000)": 9002, "Percentage of households with pets": 58.5, "Number of Pet Households (in 1000)": 5265, "Percentage of Dog Owners": 44.0, "Dog Owning Households (1000s)": 3960, "Mean Number of Dogs per household": 1.8, "Dog Population (in 1000)": 7163, "Percentage of Cat Owners": 28.3, "Cat Owning Households": 2544, "Mean Number of Cats": 2.2, "Cat Population": 5565}, {"Location": "Utah", "Number of Households (in 1000)": 930, "Percentage of households with pets": 51.2, "Number of Pet Households (in 1000)": 476, "Percentage of Dog Owners": 29.4, "Dog Owning Households (1000s)": 273, "Mean Number of Dogs per household": 1.5, "Dog Population (in 1000)": 410, "Percentage of Cat Owners": 24.6, "Cat Owning Households": 229, "Mean Number of Cats": 2.0, "Cat Population": 455}, {"Location": "Vermont", "Number of Households (in 1000)": 265, "Percentage of households with pets": 70.8, "Number of Pet Households (in 1000)": 188, "Percentage of Dog Owners": 37.7, "Dog Owning Households (1000s)": 100, "Mean Number of Dogs per household": 1.4, "Dog Population (in 1000)": 142, "Percentage of Cat Owners": 49.5, "Cat Owning Households": 131, "Mean Number of Cats": 1.8, "Cat Population": 234}, {"Location": "Virginia", "Number of Households (in 1000)": 3017, "Percentage of households with pets": 53.4, "Number of Pet Households (in 1000)": 1611, "Percentage of Dog Owners": 35.4, "Dog Owning Households (1000s)": 1069, "Mean Number of Dogs per household": 1.6, "Dog Population (in 1000)": 1699, "Percentage of Cat Owners": 29.0, "Cat Owning Households": 876, "Mean Number of Cats": 2.1, "Cat Population": 1855}, {"Location": "Washington", "Number of Households (in 1000)": 2632, "Percentage of households with pets": 62.7, "Number of Pet Households (in 1000)": 1649, "Percentage of Dog Owners": 36.3, "Dog Owning Households (1000s)": 954, "Mean Number of Dogs per household": 1.7, "Dog Population (in 1000)": 1609, "Percentage of Cat Owners": 39.0, "Cat Owning Households": 1028, "Mean Number of Cats": 1.8, "Cat Population": 1844}, {"Location": "West Virginia", "Number of Households (in 1000)": 765, "Percentage of households with pets": 62.1, "Number of Pet Households (in 1000)": 475, "Percentage of Dog Owners": 45.8, "Dog Owning Households (1000s)": 350, "Mean Number of Dogs per household": 1.8, "Dog Population (in 1000)": 648, "Percentage of Cat Owners": 38.1, "Cat Owning Households": 291, "Mean Number of Cats": 2.2, "Cat Population": 628}, {"Location": "Wisconsin", "Number of Households (in 1000)": 2350, "Percentage of households with pets": 57.5, "Number of Pet Households (in 1000)": 1352, "Percentage of Dog Owners": 33.9, "Dog Owning Households (1000s)": 796, "Mean Number of Dogs per household": 1.4, "Dog Population (in 1000)": 1138, "Percentage of Cat Owners": 33.0, "Cat Owning Households": 776, "Mean Number of Cats": 1.9, "Cat Population": 1510}, {"Location": "Wyoming", "Number of Households (in 1000)": 221, "Percentage of households with pets": 61.8, "Number of Pet Households (in 1000)": 137, "Percentage of Dog Owners": 38.8, "Dog Owning Households (1000s)": 86, "Mean Number of Dogs per household": 1.5, "Dog Population (in 1000)": 125, "Percentage of Cat Owners": 33.9, "Cat Owning Households": 75, "Mean Number of Cats": 1.9, "Cat Population": 144}]}}